[
    {
        "domain": ".upwork.com",
        "expirationDate": 1692499385.336748,
        "hostOnly": false,
        "httpOnly": true,
        "name": "e0d0933asb",
        "path": "/nx/find-work/",
        "sameSite": "unspecified",
        "secure": true,
        "session": false,
        "storeId": "0",
        "value": "oauth2v2_2da065176d7501e77a8187eacd8bb16b"
    },
    {
        "domain": ".upwork.com",
        "expirationDate": 1692541566.649726,
        "hostOnly": false,
        "httpOnly": true,
        "name": "82f2a195sb",
        "path": "/nx/find-work/",
        "sameSite": "unspecified",
        "secure": true,
        "session": false,
        "storeId": "0",
        "value": "oauth2v2_da07187ae4eece5e1be11b14d3cd5e44"
    },
    {
        "domain": ".upwork.com",
        "expirationDate": 1692548718.629099,
        "hostOnly": false,
        "httpOnly": true,
        "name": "8aef5185sb",
        "path": "/nx/find-work/",
        "sameSite": "unspecified",
        "secure": true,
        "session": false,
        "storeId": "0",
        "value": "oauth2v2_5e53dcfb76fa765541df222f649bf315"
    },
    {
        "domain": ".upwork.com",
        "expirationDate": 1724019273.421952,
        "hostOnly": false,
        "httpOnly": false,
        "name": "visitor_id",
        "path": "/",
        "sameSite": "unspecified",
        "secure": true,
        "session": false,
        "storeId": "0",
        "value": "27.73.119.23.1686975371387000"
    },
    {
        "domain": ".upwork.com",
        "expirationDate": 1694751374,
        "hostOnly": false,
        "httpOnly": false,
        "name": "_gcl_au",
        "path": "/",
        "sameSite": "unspecified",
        "secure": false,
        "session": false,
        "storeId": "0",
        "value": "1.1.2111476740.1686975374"
    },
    {
        "domain": ".upwork.com",
        "expirationDate": 1700346320,
        "hostOnly": false,
        "httpOnly": false,
        "name": "_cq_duid",
        "path": "/",
        "sameSite": "no_restriction",
        "secure": true,
        "session": false,
        "storeId": "0",
        "value": "1.1686975374.v8LdXyF5x9gYLXOI"
    },
    {
        "domain": ".upwork.com",
        "expirationDate": 1720671375,
        "hostOnly": false,
        "httpOnly": false,
        "name": "_tt_enable_cookie",
        "path": "/",
        "sameSite": "unspecified",
        "secure": false,
        "session": false,
        "storeId": "0",
        "value": "1"
    },
    {
        "domain": ".upwork.com",
        "expirationDate": 1720671375,
        "hostOnly": false,
        "httpOnly": false,
        "name": "_ttp",
        "path": "/",
        "sameSite": "unspecified",
        "secure": false,
        "session": false,
        "storeId": "0",
        "value": "YQQMe-EK6BGKZFsVP0Jcy2pn5Ts"
    },
    {
        "domain": ".upwork.com",
        "expirationDate": 1723998322.156675,
        "hostOnly": false,
        "httpOnly": true,
        "name": "spt",
        "path": "/",
        "sameSite": "no_restriction",
        "secure": true,
        "session": false,
        "storeId": "0",
        "value": "6d1b5f41-385d-484a-a85b-4b5c515b7649"
    },
    {
        "domain": ".www.upwork.com",
        "expirationDate": 1727022296.943544,
        "hostOnly": false,
        "httpOnly": false,
        "name": "G_ENABLED_IDPS",
        "path": "/",
        "sameSite": "unspecified",
        "secure": false,
        "session": false,
        "storeId": "0",
        "value": "google"
    },
    {
        "domain": ".upwork.com",
        "expirationDate": 1700238321,
        "hostOnly": false,
        "httpOnly": false,
        "name": "_rdt_uuid",
        "path": "/",
        "sameSite": "strict",
        "secure": true,
        "session": false,
        "storeId": "0",
        "value": "1686975377449.639f261f-9e5e-4c44-9ce8-1acae8756ab9"
    },
    {
        "domain": "www.upwork.com",
        "expirationDate": 1718511377,
        "hostOnly": true,
        "httpOnly": false,
        "name": "__pdst",
        "path": "/",
        "sameSite": "strict",
        "secure": false,
        "session": false,
        "storeId": "0",
        "value": "a0d6ad3f65944a608cea5fadcc1941fb"
    },
    {
        "domain": ".upwork.com",
        "expirationDate": 1700238323,
        "hostOnly": false,
        "httpOnly": false,
        "name": "_fbp",
        "path": "/",
        "sameSite": "lax",
        "secure": false,
        "session": false,
        "storeId": "0",
        "value": "fb.1.1686975377533.483013102"
    },
    {
        "domain": ".www.upwork.com",
        "expirationDate": 1727022322.283572,
        "hostOnly": false,
        "httpOnly": false,
        "name": "_zitok",
        "path": "/",
        "sameSite": "strict",
        "secure": true,
        "session": false,
        "storeId": "0",
        "value": "9f466a3c0d04570e157e1686975378"
    },
    {
        "domain": ".upwork.com",
        "expirationDate": 1718511381,
        "hostOnly": false,
        "httpOnly": false,
        "name": "OptanonAlertBoxClosed",
        "path": "/",
        "sameSite": "lax",
        "secure": false,
        "session": false,
        "storeId": "0",
        "value": "2023-06-17T04:16:21.542Z"
    },
    {
        "domain": ".upwork.com",
        "expirationDate": 1702462318.45815,
        "hostOnly": false,
        "httpOnly": false,
        "name": "recognized",
        "path": "/",
        "sameSite": "unspecified",
        "secure": true,
        "session": false,
        "storeId": "0",
        "value": "hungkv"
    },
    {
        "domain": ".upwork.com",
        "expirationDate": 1722502428.191234,
        "hostOnly": false,
        "httpOnly": false,
        "name": "_psr",
        "path": "/",
        "sameSite": "unspecified",
        "secure": false,
        "session": false,
        "storeId": "0",
        "value": "ps.2.648d5d6efafc7b0000ac7546"
    },
    {
        "domain": ".upwork.com",
        "expirationDate": 1723186810,
        "hostOnly": false,
        "httpOnly": false,
        "name": "__zlcmid",
        "path": "/",
        "sameSite": "lax",
        "secure": false,
        "session": false,
        "storeId": "0",
        "value": "1GPlu25Q41GDPLc"
    },
    {
        "domain": ".upwork.com",
        "expirationDate": 1721546145.135851,
        "hostOnly": false,
        "httpOnly": false,
        "name": "_mkto_trk",
        "path": "/",
        "sameSite": "unspecified",
        "secure": false,
        "session": false,
        "storeId": "0",
        "value": "id:518-RKL-392&token:_mch-upwork.com-1686986145135-39064"
    },
    {
        "domain": "www.upwork.com",
        "expirationDate": 1702550638,
        "hostOnly": true,
        "httpOnly": false,
        "name": "g_state",
        "path": "/",
        "sameSite": "unspecified",
        "secure": false,
        "session": false,
        "storeId": "0",
        "value": "{\"i_l\":0}"
    },
    {
        "domain": ".upwork.com",
        "expirationDate": 1695002959.533783,
        "hostOnly": false,
        "httpOnly": true,
        "name": "DA_hungkv",
        "path": "/",
        "sameSite": "unspecified",
        "secure": true,
        "session": false,
        "storeId": "0",
        "value": "14ee7f140d0449f13a3768a560061340af43f8143f642624edaddd875e9c4625"
    },
    {
        "domain": ".upwork.com",
        "expirationDate": 1719301976,
        "hostOnly": false,
        "httpOnly": false,
        "name": "lang",
        "path": "/",
        "sameSite": "lax",
        "secure": false,
        "session": false,
        "storeId": "0",
        "value": "en"
    },
    {
        "domain": ".upwork.com",
        "expirationDate": 1722928600.2666,
        "hostOnly": false,
        "httpOnly": false,
        "name": "_ga_5P89K5NWWY",
        "path": "/",
        "sameSite": "unspecified",
        "secure": false,
        "session": false,
        "storeId": "0",
        "value": "GS1.2.1688368600.1.0.1688368600.60.0.0"
    },
    {
        "domain": ".upwork.com",
        "expirationDate": 1695140721.421926,
        "hostOnly": false,
        "httpOnly": false,
        "name": "company_last_accessed",
        "path": "/",
        "sameSite": "unspecified",
        "secure": true,
        "session": false,
        "storeId": "0",
        "value": "d31015603"
    },
    {
        "domain": ".upwork.com",
        "expirationDate": 1695140721.421937,
        "hostOnly": false,
        "httpOnly": false,
        "name": "current_organization_uid",
        "path": "/",
        "sameSite": "unspecified",
        "secure": true,
        "session": false,
        "storeId": "0",
        "value": "1248534841784614913"
    },
    {
        "domain": ".upwork.com",
        "expirationDate": 1692688921.519655,
        "hostOnly": false,
        "httpOnly": true,
        "name": "device_view",
        "path": "/",
        "sameSite": "unspecified",
        "secure": true,
        "session": false,
        "storeId": "0",
        "value": "full"
    },
    {
        "domain": ".upwork.com",
        "expirationDate": 1692776619.063429,
        "hostOnly": false,
        "httpOnly": false,
        "name": "acced31015603",
        "path": "/",
        "sameSite": "unspecified",
        "secure": false,
        "session": false,
        "storeId": "0",
        "value": "31620873"
    },
    {
        "domain": "www.upwork.com",
        "expirationDate": 1725373557.758842,
        "hostOnly": true,
        "httpOnly": false,
        "name": "_sp_id.2a16",
        "path": "/",
        "sameSite": "unspecified",
        "secure": false,
        "session": false,
        "storeId": "0",
        "value": "909b6676-b340-499e-bf7f-38083afb05d4.1686975374.59.1690813558.1689486678.bf79f884-d064-441a-b5ee-f64b1e5ce673"
    },
    {
        "domain": ".upwork.com",
        "expirationDate": 1726210809.587379,
        "hostOnly": false,
        "httpOnly": false,
        "name": "_ga_SB157S2R94",
        "path": "/",
        "sameSite": "unspecified",
        "secure": false,
        "session": false,
        "storeId": "0",
        "value": "GS1.2.1691650724.17.1.1691650809.60.0.0"
    },
    {
        "domain": "www.upwork.com",
        "expirationDate": 1692689605.276323,
        "hostOnly": true,
        "httpOnly": true,
        "name": "__cflb",
        "path": "/",
        "sameSite": "no_restriction",
        "secure": true,
        "session": false,
        "storeId": "0",
        "value": "02DiuEXPXZVk436fJfSVuuwDqLqkhavJbGWFRFoxEj5L7"
    },
    {
        "domain": ".upwork.com",
        "expirationDate": 1692548720,
        "hostOnly": false,
        "httpOnly": false,
        "name": "_gid",
        "path": "/",
        "sameSite": "unspecified",
        "secure": false,
        "session": false,
        "storeId": "0",
        "value": "GA1.2.642642419.1692174958"
    },
    {
        "domain": ".upwork.com",
        "expirationDate": 1707905851.276534,
        "hostOnly": false,
        "httpOnly": false,
        "name": "umq",
        "path": "/",
        "sameSite": "unspecified",
        "secure": true,
        "session": false,
        "storeId": "0",
        "value": "1920"
    },
    {
        "domain": ".upwork.com",
        "expirationDate": 1692499552.567718,
        "hostOnly": false,
        "httpOnly": false,
        "name": "profile_vv_gql_token",
        "path": "/",
        "sameSite": "unspecified",
        "secure": true,
        "session": false,
        "storeId": "0",
        "value": "oauth2v2_17277e137b82cf22d67483ddc31cbbee"
    },
    {
        "domain": ".upwork.com",
        "expirationDate": 1692499384.568033,
        "hostOnly": false,
        "httpOnly": true,
        "name": "fe6f4f4sb",
        "path": "/",
        "sameSite": "unspecified",
        "secure": true,
        "session": false,
        "storeId": "0",
        "value": "oauth2v2_01ef645a0354b4c17980d3a0eac7eecb"
    },
    {
        "domain": ".upwork.com",
        "expirationDate": 1692499554.74898,
        "hostOnly": false,
        "httpOnly": false,
        "name": "att_vt",
        "path": "/",
        "sameSite": "unspecified",
        "secure": true,
        "session": false,
        "storeId": "0",
        "value": "oauth2v2_f2b70f7d2001b45e3dcf027fe8070ea3"
    },
    {
        "domain": ".upwork.com",
        "expirationDate": 1692499384.749001,
        "hostOnly": false,
        "httpOnly": true,
        "name": "7a53400asb",
        "path": "/",
        "sameSite": "unspecified",
        "secure": true,
        "session": false,
        "storeId": "0",
        "value": "oauth2v2_8b026893bc5e3ca1dd7f15ee961c08b4"
    },
    {
        "domain": ".upwork.com",
        "expirationDate": 1692499635.526339,
        "hostOnly": false,
        "httpOnly": false,
        "name": "vjd_gql_token",
        "path": "/",
        "sameSite": "unspecified",
        "secure": true,
        "session": false,
        "storeId": "0",
        "value": "oauth2v2_01ac606a871fec7259ce6d5a17b2a929"
    },
    {
        "domain": "www.upwork.com",
        "expirationDate": 1692523920,
        "hostOnly": true,
        "httpOnly": false,
        "name": "ln_or",
        "path": "/",
        "sameSite": "unspecified",
        "secure": false,
        "session": false,
        "storeId": "0",
        "value": "eyI2MzgxNCI6ImQifQ%3D%3D"
    },
    {
        "domain": ".upwork.com",
        "hostOnly": false,
        "httpOnly": false,
        "name": "country_code",
        "path": "/",
        "sameSite": "unspecified",
        "secure": true,
        "session": true,
        "storeId": "0",
        "value": "VN"
    },
    {
        "domain": "www.upwork.com",
        "hostOnly": true,
        "httpOnly": false,
        "name": "cookie_prefix",
        "path": "/",
        "sameSite": "unspecified",
        "secure": true,
        "session": true,
        "storeId": "0",
        "value": ""
    },
    {
        "domain": "www.upwork.com",
        "hostOnly": true,
        "httpOnly": false,
        "name": "cookie_domain",
        "path": "/",
        "sameSite": "unspecified",
        "secure": true,
        "session": true,
        "storeId": "0",
        "value": ".upwork.com"
    },
    {
        "domain": ".upwork.com",
        "expirationDate": 1692464095.30106,
        "hostOnly": false,
        "httpOnly": true,
        "name": "__cf_bm",
        "path": "/",
        "sameSite": "no_restriction",
        "secure": true,
        "session": false,
        "storeId": "0",
        "value": "1E162FTGQHZ60ovcZTzk5GMD.Fzju1fQqYuZTPn3VjU-1692462294-0-Adfj3sGr2Kw+cLZAl/V9WhsuQRjlErWvhMOeNQjZYQkNwmQ/SCNf718K/sBEQc4rUWhpZJ8A94yKpgn2LoTOjHU="
    },
    {
        "domain": ".upwork.com",
        "hostOnly": false,
        "httpOnly": true,
        "name": "_cfuvid",
        "path": "/",
        "sameSite": "no_restriction",
        "secure": true,
        "session": true,
        "storeId": "0",
        "value": "Ujx6g085gZTEUGr1n_xh0aOs29B81eGWLMmFxtlnfTw-1692462294896-0-604800000"
    },
    {
        "domain": ".upwork.com",
        "expirationDate": 1692466616,
        "hostOnly": false,
        "httpOnly": false,
        "name": "ftr_blst_1h",
        "path": "/",
        "sameSite": "unspecified",
        "secure": false,
        "session": false,
        "storeId": "0",
        "value": "1692462296458"
    },
    {
        "domain": ".upwork.com",
        "expirationDate": 1692548696.69422,
        "hostOnly": false,
        "httpOnly": false,
        "name": "asct_vt",
        "path": "/",
        "sameSite": "unspecified",
        "secure": true,
        "session": false,
        "storeId": "0",
        "value": "oauth2v2_fe316b5ad276ebe1a46014ab0fa4856a"
    },
    {
        "domain": ".upwork.com",
        "hostOnly": false,
        "httpOnly": false,
        "name": "_cq_suid",
        "path": "/",
        "sameSite": "no_restriction",
        "secure": true,
        "session": true,
        "storeId": "0",
        "value": "1.1692462296.MSj9vgvDjp57oY0g"
    },
    {
        "domain": ".upwork.com",
        "expirationDate": 1692464121,
        "hostOnly": false,
        "httpOnly": false,
        "name": "_upw_ses.5831",
        "path": "/",
        "sameSite": "no_restriction",
        "secure": true,
        "session": false,
        "storeId": "0",
        "value": "*"
    },
    {
        "domain": ".upwork.com",
        "expirationDate": 1692462356,
        "hostOnly": false,
        "httpOnly": false,
        "name": "_dc_gtm_UA-62227314-1",
        "path": "/",
        "sameSite": "unspecified",
        "secure": false,
        "session": false,
        "storeId": "0",
        "value": "1"
    },
    {
        "domain": ".upwork.com",
        "hostOnly": false,
        "httpOnly": false,
        "name": "IR_gbd",
        "path": "/",
        "sameSite": "unspecified",
        "secure": false,
        "session": true,
        "storeId": "0",
        "value": "upwork.com"
    },
    {
        "domain": ".upwork.com",
        "hostOnly": false,
        "httpOnly": true,
        "name": "console_user",
        "path": "/",
        "sameSite": "unspecified",
        "secure": true,
        "session": true,
        "storeId": "0",
        "value": "hungkv"
    },
    {
        "domain": ".upwork.com",
        "hostOnly": false,
        "httpOnly": true,
        "name": "user_uid",
        "path": "/",
        "sameSite": "unspecified",
        "secure": true,
        "session": true,
        "storeId": "0",
        "value": "1248534841738477568"
    },
    {
        "domain": ".upwork.com",
        "hostOnly": false,
        "httpOnly": true,
        "name": "master_access_token",
        "path": "/",
        "sameSite": "unspecified",
        "secure": true,
        "session": true,
        "storeId": "0",
        "value": "b986fe8f.oauth2v2_50c4c959c6f60514c71407eedf37d261"
    },
    {
        "domain": ".upwork.com",
        "hostOnly": false,
        "httpOnly": false,
        "name": "oauth2_global_js_token",
        "path": "/",
        "sameSite": "unspecified",
        "secure": true,
        "session": true,
        "storeId": "0",
        "value": "oauth2v2_a3f522774a7a299231fb505c9fda536d"
    },
    {
        "domain": ".upwork.com",
        "hostOnly": false,
        "httpOnly": true,
        "name": "SZ",
        "path": "/",
        "sameSite": "unspecified",
        "secure": true,
        "session": true,
        "storeId": "0",
        "value": "1b1c9dab239246b86d21d4cdeb0d43613de06d64845b4caf5c25a62548941594"
    },
    {
        "domain": ".upwork.com",
        "expirationDate": 1723998320,
        "hostOnly": false,
        "httpOnly": false,
        "name": "OptanonConsent",
        "path": "/",
        "sameSite": "lax",
        "secure": false,
        "session": false,
        "storeId": "0",
        "value": "isGpcEnabled=0&datestamp=Sat+Aug+19+2023+23%3A25%3A20+GMT%2B0700+(Indochina+Time)&version=202305.1.0&browserGpcFlag=0&isIABGlobal=false&hosts=&consentId=0527c32b-1503-4e1f-917a-658abede1223&interactionCount=2&landingPath=NotLandingPage&groups=C0001%3A1%2CC0002%3A1%2CC0003%3A1%2CC0004%3A1&AwaitingReconsent=false&geolocation=VN%3BHN"
    },
    {
        "domain": ".upwork.com",
        "hostOnly": false,
        "httpOnly": false,
        "name": "XSRF-TOKEN",
        "path": "/",
        "sameSite": "unspecified",
        "secure": true,
        "session": true,
        "storeId": "0",
        "value": "de55e860b25ef01dcd1e90413330d03b"
    },
    {
        "domain": ".upwork.com",
        "expirationDate": 1692545118.421961,
        "hostOnly": false,
        "httpOnly": true,
        "name": "user_oauth2_slave_access_token",
        "path": "/",
        "sameSite": "unspecified",
        "secure": true,
        "session": false,
        "storeId": "0",
        "value": "b986fe8f.oauth2v2_50c4c959c6f60514c71407eedf37d261:1248534841738477568.oauth2v2_bca82b7263578f8ae3d80c827d0bcf0e"
    },
    {
        "domain": ".upwork.com",
        "hostOnly": false,
        "httpOnly": false,
        "name": "IR_13634",
        "path": "/",
        "sameSite": "unspecified",
        "secure": false,
        "session": true,
        "storeId": "0",
        "value": "1692462321535%7C0%7C1692462321535%7C%7C"
    },
    {
        "domain": ".upwork.com",
        "expirationDate": 1692548721,
        "hostOnly": false,
        "httpOnly": false,
        "name": "_uetsid",
        "path": "/",
        "sameSite": "unspecified",
        "secure": false,
        "session": false,
        "storeId": "0",
        "value": "ed4cd2b03c0f11ee88164ff38ec1ff02"
    },
    {
        "domain": ".upwork.com",
        "expirationDate": 1726158321,
        "hostOnly": false,
        "httpOnly": false,
        "name": "_uetvid",
        "path": "/",
        "sameSite": "unspecified",
        "secure": false,
        "session": false,
        "storeId": "0",
        "value": "b4a69f400cc511eebbe6c37643b0b278"
    },
    {
        "domain": ".upwork.com",
        "expirationDate": 1727022321.571448,
        "hostOnly": false,
        "httpOnly": false,
        "name": "_ga_KSM221PNDX",
        "path": "/",
        "sameSite": "unspecified",
        "secure": false,
        "session": false,
        "storeId": "0",
        "value": "GS1.1.1692462298.178.1.1692462321.0.0.0"
    },
    {
        "domain": ".upwork.com",
        "expirationDate": 1727022321.571648,
        "hostOnly": false,
        "httpOnly": false,
        "name": "_ga",
        "path": "/",
        "sameSite": "unspecified",
        "secure": false,
        "session": false,
        "storeId": "0",
        "value": "GA1.1.1663573506.1686975374"
    },
    {
        "domain": ".upwork.com",
        "expirationDate": 1727022321.645153,
        "hostOnly": false,
        "httpOnly": false,
        "name": "_upw_id.5831",
        "path": "/",
        "sameSite": "no_restriction",
        "secure": true,
        "session": false,
        "storeId": "0",
        "value": "909b6676-b340-499e-bf7f-38083afb05d4.1686975374.177.1692462322.1692455245.e1d0ff10-ced1-48c0-820f-17b7786fda1e.39ad7588-0177-46bf-bc52-8ab0c6bea944.5935e06c-8f17-4a14-bef3-8c68fcdd13e2.1692462296920.17"
    },
    {
        "domain": ".upwork.com",
        "expirationDate": 1727022321,
        "hostOnly": false,
        "httpOnly": false,
        "name": "forterToken",
        "path": "/",
        "sameSite": "unspecified",
        "secure": false,
        "session": false,
        "storeId": "0",
        "value": "80a9e0d30451401da8deb33186371dd9_1692462320575__UDF43-m4_14ck"
    },
    {
        "domain": "www.upwork.com",
        "hostOnly": true,
        "httpOnly": false,
        "name": "enabled_ff",
        "path": "/",
        "sameSite": "unspecified",
        "secure": true,
        "session": true,
        "storeId": "0",
        "value": "!TONB3476Air3Migration,!JPAir3,!RMTAir3Talent,!air2Dot76Qt,!CI10270Air2Dot5QTAllocations,!CI10857Air3Dot0,CI11132Air2Dot75,air2Dot76,CI9570Air2Dot5,!pxWTA3,!SSINavUser,!MP16400Air3Migration,i18nOn,OTBnrOn,!CI12577UniversalSearch,!pxFAA3,!pxBPA3,TONB2256Air3Migration,!pxGPA3,pxTHA3"
    },
    {
        "domain": "www.upwork.com",
        "expirationDate": 1693067122.156282,
        "hostOnly": true,
        "httpOnly": false,
        "name": "AWSALB",
        "path": "/",
        "sameSite": "unspecified",
        "secure": false,
        "session": false,
        "storeId": "0",
        "value": "zIMPw1CBzlGPkGrBkxZSRxVKPtM3OTvMkCv7dFj2eh1ecTlM0mX8XW0p5uwU6IrL9HVAiEWbMMK6rhanDTT5Y6v6UN2EUxYTMgZB7ZRGmC+rABc50AAF9J96gR+F"
    },
    {
        "domain": "www.upwork.com",
        "expirationDate": 1693067122.156544,
        "hostOnly": true,
        "httpOnly": false,
        "name": "AWSALBCORS",
        "path": "/",
        "sameSite": "no_restriction",
        "secure": true,
        "session": false,
        "storeId": "0",
        "value": "zIMPw1CBzlGPkGrBkxZSRxVKPtM3OTvMkCv7dFj2eh1ecTlM0mX8XW0p5uwU6IrL9HVAiEWbMMK6rhanDTT5Y6v6UN2EUxYTMgZB7ZRGmC+rABc50AAF9J96gR+F"
    }
]